potc_dict/__init__.py
potc_dict/plugin.py
potc_dict/config/__init__.py
potc_dict/config/meta.py
potc_dict-0.0.3.dist-info/LICENSE
potc_dict-0.0.3.dist-info/METADATA
potc_dict-0.0.3.dist-info/WHEEL
potc_dict-0.0.3.dist-info/entry_points.txt
potc_dict-0.0.3.dist-info/top_level.txt
potc_dict-0.0.3.dist-info/RECORD
